Metadata-Version: 2.1
Name: sem-6-package-1
Version: 1.0.0
Summary: первый пакет из домашки
Author-email: brxbxt <89297578555a@gmail.com>
License: MIT
Requires-Python: >=3.12
Requires-Dist: requests>=2.25.1
